recommed_api/__init__.py
recommed_api/tools/__init__.py
recommed_api/tools/recommed_api_tool.py
recommed_api/tools/utils.py
recommed_api/yamls/recommed_api_tool.yaml
tests/__init__.py
tests/test_recommed_api_tool.py
recommed_api-0.0.2.dist-info/METADATA
recommed_api-0.0.2.dist-info/WHEEL
recommed_api-0.0.2.dist-info/entry_points.txt
recommed_api-0.0.2.dist-info/top_level.txt
recommed_api-0.0.2.dist-info/RECORD
